pycht/__init__.py
pycht/cli.py
pycht/clustering.py
pycht/image_processing.py
pycht/pycht.py
pycht-0.1.21.dist-info/licenses/LICENSE
pycht-0.1.21.dist-info/METADATA
pycht-0.1.21.dist-info/WHEEL
pycht-0.1.21.dist-info/entry_points.txt
pycht-0.1.21.dist-info/top_level.txt
pycht-0.1.21.dist-info/RECORD
