Metadata-Version: 2.4
Name: pycht
Version: 0.1.21
Summary: Street art by clustering.
Project-URL: Repository, https://github.com/tlentali/pycht
Project-URL: Documentation, https://tlentali.github.io/pycht/
Requires-Python: >=3.12
License-File: LICENSE
Requires-Dist: pillow>=11.2.1
Requires-Dist: scikit-learn>=1.6.1
Requires-Dist: typer
Requires-Dist: typing-extensions
Dynamic: license-file
